html_telegraph_poster/__init__.py
html_telegraph_poster/converter.py
html_telegraph_poster/create_account.py
html_telegraph_poster/errors.py
html_telegraph_poster/html_to_telegraph.py
html_telegraph_poster/upload_images.py
html_telegraph_poster/utils.py
html_telegraph_poster-0.5.0.dist-info/LICENSE
html_telegraph_poster-0.5.0.dist-info/METADATA
html_telegraph_poster-0.5.0.dist-info/WHEEL
html_telegraph_poster-0.5.0.dist-info/top_level.txt
html_telegraph_poster-0.5.0.dist-info/RECORD
